vm_pkg_tools/__init__.py
vm_pkg_tools/core/__init__.py
vm_pkg_tools/core/main.py
vm_pkg_tools/core/orchestrator.py
vm_pkg_tools/parsers/__init__.py
vm_pkg_tools/parsers/advanced/__init__.py
vm_pkg_tools/parsers/advanced/parse_more.py
vm_pkg_tools/parsers/match_actions/__init__.py
vm_pkg_tools/parsers/match_actions/lineups_parser.py
vm_pkg_tools/parsers/match_actions/match_actions_parser.py
vm_pkg_tools/parsers/match_actions/points_parser.py
vm_pkg_tools/parsers/match_actions/set_parser.py
vm_pkg_tools/parsers/metadata/__init__.py
vm_pkg_tools/parsers/metadata/comments_parser.py
vm_pkg_tools/parsers/metadata/metadata_parser.py
vm_pkg_tools/parsers/sets_results/__init__.py
vm_pkg_tools/parsers/sets_results/sets_parser.py
vm_pkg_tools/parsers/teams_and_players/__init__.py
vm_pkg_tools/parsers/teams_and_players/players_parser.py
vm_pkg_tools/parsers/teams_and_players/teams_parser.py
vm_pkg_tools/utils/__init__.py
vm_pkg_tools/utils/base_parser.py
vm_pkg_tools/utils/exceptions.py
vm_pkg_tools/utils/file_utils.py
vm_pkg_tools/utils/logger.py
vm_pkg_tools/utils/parser_utils.py
vm_pkg_tools/validators/__init__.py
vm_pkg_tools/validators/data_validator.py
vm_pkg_tools/validators/schema_validator.py
vm_pkg_tools-1.0.25.dist-info/licenses/LICENSE
vm_pkg_tools-1.0.25.dist-info/METADATA
vm_pkg_tools-1.0.25.dist-info/WHEEL
vm_pkg_tools-1.0.25.dist-info/entry_points.txt
vm_pkg_tools-1.0.25.dist-info/top_level.txt
vm_pkg_tools-1.0.25.dist-info/RECORD
