Metadata-Version: 2.4
Name: vm-pkg-tools
Version: 1.0.25
Summary: A private package for scout file parsing.
Home-page: https://github.com/volleymateteam/scout_parser_py
Author: Reza Barzegar Gashti
Author-email: rezabarzegargashti@gmail.com
License: Proprietary
Keywords: volleyball,parser,dvw,scout files
Classifier: Programming Language :: Python :: 3
Classifier: License :: Other/Proprietary License
Classifier: Operating System :: OS Independent
Classifier: Intended Audience :: Developers
Classifier: Topic :: Software Development :: Libraries :: Python Modules
Requires-Python: >=3.10
License-File: LICENSE
Requires-Dist: click<9.0,>=8.1
Requires-Dist: pydantic<3.0,>=2.0
Requires-Dist: sqlalchemy<3.0,>=2.0
Requires-Dist: PyYAML<7.0,>=6.0
Requires-Dist: unidecode<2.0,>=1.3
Requires-Dist: chardet<6.0,>=5.0
Requires-Dist: colorlog<7.0,>=6.0
Requires-Dist: jsonschema<5.0,>=4.0
Provides-Extra: dev
Requires-Dist: setuptools>=65.5; extra == "dev"
Requires-Dist: twine>=4.0.0; extra == "dev"
Requires-Dist: black>=24.10; extra == "dev"
Requires-Dist: flake8>=7.1; extra == "dev"
Requires-Dist: isort>=5.13; extra == "dev"
Requires-Dist: pylint>=3.3; extra == "dev"
Requires-Dist: pytest>=8.3.4; extra == "dev"
Requires-Dist: attrs>=24.3; extra == "dev"
Dynamic: author
Dynamic: author-email
Dynamic: classifier
Dynamic: description
Dynamic: description-content-type
Dynamic: home-page
Dynamic: keywords
Dynamic: license
Dynamic: license-file
Dynamic: provides-extra
Dynamic: requires-dist
Dynamic: requires-python
Dynamic: summary
